ChameleonClient-0.1.0.dist-info/DESCRIPTION.rst
ChameleonClient-0.1.0.dist-info/METADATA
ChameleonClient-0.1.0.dist-info/RECORD
ChameleonClient-0.1.0.dist-info/WHEEL
ChameleonClient-0.1.0.dist-info/metadata.json
ChameleonClient-0.1.0.dist-info/pbr.json
ChameleonClient-0.1.0.dist-info/top_level.txt
chameleon/__init__.py
