Metadata-Version: 2.0
Name: ChameleonClient
Version: 0.1.0
Summary: Simple client for the Chameleon mock server
Home-page: https://github.com/jolleon/chameleon
Author: Jules Olleon
Author-email: jolleon@gmail.com
License: WTFPL
Platform: UNKNOWN
Classifier: Environment :: Web Environment
Classifier: Intended Audience :: Developers
Classifier: License :: Public Domain
Classifier: Operating System :: OS Independent
Classifier: Programming Language :: Python
Classifier: Programming Language :: Python :: 2
Classifier: Programming Language :: Python :: 3
Classifier: Topic :: Internet :: WWW/HTTP
Classifier: Topic :: Software Development :: Testing
Classifier: Topic :: Software Development :: Libraries :: Python Modules
Requires-Dist: requests (>=2.10.0)
Requires-Dist: docker
